pytensor_ml/__init__.py
pytensor_ml/_version.py
pytensor_ml/activations.py
pytensor_ml/layers.py
pytensor_ml/loss.py
pytensor_ml/model.py
pytensor_ml/optimizers.py
pytensor_ml/pytensorf.py
pytensor_ml/util.py
pytensor_ml/rewriting/__init__.py
pytensor_ml/rewriting/layers.py
pytensor_ml-0.0.3.dist-info/LICENSE
pytensor_ml-0.0.3.dist-info/METADATA
pytensor_ml-0.0.3.dist-info/WHEEL
pytensor_ml-0.0.3.dist-info/top_level.txt
pytensor_ml-0.0.3.dist-info/RECORD
