Metadata-Version: 2.1
Name: pytensor-ml
Version: 0.0.3
Summary: A(nother) deep learning library, built on top of Pytensor
Author: Ricardo Vieira
Author-email: Jesse Grabowski <jessegrabowski@gmail.com>
License: Apache License
Keywords: neural network,deep learning,autograd,gradient descent,pymc
Classifier: Development Status :: 2 - Pre-Alpha
Classifier: Intended Audience :: Science/Research
Classifier: Programming Language :: Python
Classifier: Topic :: Scientific/Engineering
Classifier: Operating System :: Microsoft :: Windows
Classifier: Operating System :: POSIX
Classifier: Operating System :: Unix
Classifier: Operating System :: MacOS
Classifier: Programming Language :: Python :: 3
Classifier: Programming Language :: Python :: 3.10
Classifier: Programming Language :: Python :: 3.11
Classifier: Programming Language :: Python :: 3.12
License-File: LICENSE
Requires-Dist: pytensor
Requires-Dist: numpy
Requires-Dist: pymc
Provides-Extra: dev
Requires-Dist: pre-commit; extra == "dev"
Requires-Dist: pytest; extra == "dev"
Requires-Dist: pytest-cov; extra == "dev"
Requires-Dist: versioneer; extra == "dev"
Requires-Dist: scikit-learn; extra == "dev"
